tlc_ultralytics/__init__.py
tlc_ultralytics/_static/dashboard.png
tlc_ultralytics/classify/__init__.py
tlc_ultralytics/classify/dataset.py
tlc_ultralytics/classify/trainer.py
tlc_ultralytics/classify/utils.py
tlc_ultralytics/classify/validator.py
tlc_ultralytics/constants.py
tlc_ultralytics/detect/__init__.py
tlc_ultralytics/detect/dataset.py
tlc_ultralytics/detect/loss.py
tlc_ultralytics/detect/trainer.py
tlc_ultralytics/detect/utils.py
tlc_ultralytics/detect/validator.py
tlc_ultralytics/engine/__init__.py
tlc_ultralytics/engine/dataset.py
tlc_ultralytics/engine/model.py
tlc_ultralytics/engine/trainer.py
tlc_ultralytics/engine/utils.py
tlc_ultralytics/engine/validator.py
tlc_ultralytics/obb/__init__.py
tlc_ultralytics/obb/dataset.py
tlc_ultralytics/obb/trainer.py
tlc_ultralytics/obb/utils.py
tlc_ultralytics/obb/validator.py
tlc_ultralytics/overrides.py
tlc_ultralytics/pose/__init__.py
tlc_ultralytics/pose/dataset.py
tlc_ultralytics/pose/loss.py
tlc_ultralytics/pose/trainer.py
tlc_ultralytics/pose/utils.py
tlc_ultralytics/pose/validator.py
tlc_ultralytics/segment/__init__.py
tlc_ultralytics/segment/trainer.py
tlc_ultralytics/segment/utils.py
tlc_ultralytics/segment/validator.py
tlc_ultralytics/settings.py
tlc_ultralytics/utils/__init__.py
tlc_ultralytics/utils/check_requirements.py
tlc_ultralytics/utils/dataset.py
tlc_ultralytics/utils/embeddings.py
tlc_ultralytics/utils/generate_ddp.py
tlc_ultralytics/utils/sampler.py
tlc_ultralytics/utils/schemas.py
3lc_ultralytics-0.1.7.dist-info/WHEEL
3lc_ultralytics-0.1.7.dist-info/METADATA
3lc_ultralytics-0.1.7.dist-info/RECORD
