Metadata-Version: 2.3
Name: 3lc-ultralytics
Version: 0.1.7
Summary: 3LC integration with Ultralytics YOLO
Author: 3LC
Author-email: 3LC <support@3lc.ai>
Requires-Dist: 3lc>=2.18.0,<3.0.0
Requires-Dist: pacmap>=0.8.0
Requires-Dist: ultralytics>=8.4.0,<8.4.7
Requires-Python: >=3.9, <3.14
